[
  {
    "timestamp": 1779758241005,
    "score": 56
  },
  {
    "timestamp": 1779759315696,
    "score": 56
  },
  {
    "timestamp": 1779759540495,
    "score": 56
  },
  {
    "timestamp": 1779761306957,
    "score": 56
  },
  {
    "timestamp": 1779762107575,
    "score": 56
  },
  {
    "timestamp": 1779788375037,
    "score": 58
  },
  {
    "timestamp": 1779841257509,
    "score": 58
  },
  {
    "timestamp": 1779935259709,
    "score": 58
  },
  {
    "timestamp": 1780014348467,
    "score": 58
  },
  {
    "timestamp": 1780102671979,
    "score": 59
  },
  {
    "timestamp": 1780197251404,
    "score": 59
  },
  {
    "timestamp": 1780280661070,
    "score": 59
  }
]